gaspump/__init__.py
gaspump/api/.gitkeep
gaspump/api/__init__.py
gaspump/contracts/__init__.py
gaspump/contracts/GaspumpJetton.py
gaspump/contracts/JettonWallet.py
gaspump/enums.py
gaspump/models.py
gaspump/utils/__init__.py
gaspump/utils/utils.py
gaspump-1.0.0.dist-info/LICENSE
gaspump-1.0.0.dist-info/METADATA
gaspump-1.0.0.dist-info/WHEEL
gaspump-1.0.0.dist-info/RECORD
