Metadata-Version: 2.1
Name: gaspump
Version: 1.0.0
Summary: SDK on python for GasPump.
Author: littlecat-dev
Requires-Python: >=3.10,<4.0
Classifier: Programming Language :: Python :: 3
Classifier: Programming Language :: Python :: 3.10
Classifier: Programming Language :: Python :: 3.11
Classifier: Programming Language :: Python :: 3.12
Requires-Dist: pydantic-settings (>=2.3.4,<3.0.0)
Requires-Dist: pytoniq (>=0.1.39,<0.2.0)
